LICENSE.txt
MANIFEST.in
README.md
pyatmo.py
setup.cfg
setup.py
pyatmo_fork.egg-info/PKG-INFO
pyatmo_fork.egg-info/SOURCES.txt
pyatmo_fork.egg-info/dependency_links.txt
pyatmo_fork.egg-info/top_level.txt
smart_home/Camera.py
smart_home/HomeCoach.py
smart_home/PublicData.py
smart_home/Thermostat.py
smart_home/WeatherStation.py
smart_home/__init__.py